hnt_sap_gui/__init__.py
hnt_sap_gui/hnt_sap.py
hnt_sap_gui/hnt_sap_exception.py
hnt_sap_gui/common/session.py
hnt_sap_gui/fornecedor/XK03_transaction.py
hnt_sap_fornecedor_library-0.0.1.dist-info/METADATA
hnt_sap_fornecedor_library-0.0.1.dist-info/WHEEL
hnt_sap_fornecedor_library-0.0.1.dist-info/top_level.txt
hnt_sap_fornecedor_library-0.0.1.dist-info/RECORD
