Metadata-Version: 2.4
Name: hnt_sap_fornecedor_library
Version: 0.0.1
Summary: Lib para ler dados do fornecedor.
Author: Pepe
Maintainer: Pepe
License: MIT License
Keywords: Dados do fornecedor SAP
Requires-Dist: python-dotenv
Requires-Dist: robotframework-sapguilibrary
Dynamic: author
Dynamic: keywords
Dynamic: license
Dynamic: maintainer
Dynamic: requires-dist
Dynamic: summary
